mkdocs_auto_figure_list/__init__.py
mkdocs_auto_figure_list/plugin.py
mkdocs_auto_figure_list-0.2.2.dist-info/licenses/LICENSE
mkdocs_auto_figure_list-0.2.2.dist-info/METADATA
mkdocs_auto_figure_list-0.2.2.dist-info/WHEEL
mkdocs_auto_figure_list-0.2.2.dist-info/entry_points.txt
mkdocs_auto_figure_list-0.2.2.dist-info/top_level.txt
mkdocs_auto_figure_list-0.2.2.dist-info/RECORD
