Metadata-Version: 2.4
Name: mkdocs-auto-figure-list
Version: 0.2.2
Summary: Auto creation for figures in MkDocs.
Home-page: https://github.com/Privatacc/mkdocs-auto-figure-list
Author: privatacc
Project-URL: Source, https://github.com/Privatacc/mkdocs-auto-figure-list
Project-URL: Tracker, https://github.com/Privatacc/mkdocs-auto-figure-list/issues
License-File: LICENSE
Requires-Dist: mkdocs
Dynamic: author
Dynamic: description
Dynamic: description-content-type
Dynamic: home-page
Dynamic: license-file
Dynamic: project-url
Dynamic: requires-dist
Dynamic: summary
